connexion/__init__.py
connexion/__main__.py
connexion/apps/__init__.py
connexion/apps/abstract.py
connexion/apps/asynchronous.py
connexion/apps/flask.py
connexion/cli.py
connexion/context.py
connexion/datastructures.py
connexion/decorators/__init__.py
connexion/decorators/main.py
connexion/decorators/parameter.py
connexion/decorators/response.py
connexion/exceptions.py
connexion/frameworks/__init__.py
connexion/frameworks/abstract.py
connexion/frameworks/flask.py
connexion/frameworks/starlette.py
connexion/handlers.py
connexion/http_facts.py
connexion/json_schema.py
connexion/jsonifier.py
connexion/lifecycle.py
connexion/middleware/__init__.py
connexion/middleware/abstract.py
connexion/middleware/context.py
connexion/middleware/exceptions.py
connexion/middleware/lifespan.py
connexion/middleware/main.py
connexion/middleware/request_validation.py
connexion/middleware/response_validation.py
connexion/middleware/routing.py
connexion/middleware/security.py
connexion/middleware/server_error.py
connexion/middleware/swagger_ui.py
connexion/mock.py
connexion/operations/__init__.py
connexion/operations/abstract.py
connexion/operations/openapi.py
connexion/operations/swagger2.py
connexion/options.py
connexion/problem.py
connexion/resolver.py
connexion/resources/schemas/v2.0/schema.json
connexion/resources/schemas/v3.0/schema.json
connexion/security.py
connexion/spec.py
connexion/testing.py
connexion/types.py
connexion/uri_parsing.py
connexion/utils.py
connexion/validators/__init__.py
connexion/validators/abstract.py
connexion/validators/form_data.py
connexion/validators/json.py
connexion/validators/parameter.py
connexion-3.0.4.dist-info/LICENSE
connexion-3.0.4.dist-info/METADATA
connexion-3.0.4.dist-info/WHEEL
connexion-3.0.4.dist-info/entry_points.txt
connexion-3.0.4.dist-info/RECORD
