Metadata-Version: 2.1
Name: connexion
Version: 3.0.4
Summary: Connexion - API first applications with OpenAPI/Swagger
Home-page: https://github.com/spec-first/connexion
License: Apache-2.0
Keywords: api,swagger,openapi
Author: Robbe Sneyders
Author-email: robbe.sneyders@gmail.com
Maintainer: Robbe Sneyders
Maintainer-email: robbe.sneyders@gmail.com
Requires-Python: >=3.8,<4.0
Classifier: Development Status :: 5 - Production/Stable
Classifier: Intended Audience :: Developers
Classifier: License :: OSI Approved :: Apache Software License
Classifier: Operating System :: OS Independent
Classifier: Programming Language :: Python
Classifier: Programming Language :: Python :: 3
Classifier: Programming Language :: Python :: 3.8
Classifier: Programming Language :: Python :: 3.9
Classifier: Programming Language :: Python :: 3.10
Classifier: Programming Language :: Python :: 3.11
Classifier: Programming Language :: Python :: 3.12
Classifier: Programming Language :: Python :: 3 :: Only
Classifier: Topic :: Internet
Classifier: Topic :: Internet :: WWW/HTTP
Classifier: Topic :: Internet :: WWW/HTTP :: HTTP Servers
Classifier: Topic :: Software Development
Classifier: Topic :: Software Development :: Libraries
Classifier: Topic :: Software Development :: Libraries :: Python Modules
Classifier: Typing :: Typed
Provides-Extra: flask
Provides-Extra: swagger-ui
Provides-Extra: uvicorn
Requires-Dist: Jinja2 (>=3.0.0)
Requires-Dist: PyYAML (>=5.1)
Requires-Dist: a2wsgi (>=1.7) ; extra == "flask"
Requires-Dist: asgiref (>=3.4)
Requires-Dist: flask[async] (>=2.2) ; extra == "flask"
Requires-Dist: httpx (>=0.23)
Requires-Dist: inflection (>=0.3.1)
Requires-Dist: jsonschema (>=4.0.1)
Requires-Dist: python-multipart (>=0.0.5)
Requires-Dist: requests (>=2.27)
Requires-Dist: starlette (>=0.27,<0.33)
Requires-Dist: swagger-ui-bundle (>=1.1.0) ; extra == "swagger-ui"
Requires-Dist: typing-extensions (>=4)
Requires-Dist: uvicorn[standard] (>=0.17.6) ; extra == "uvicorn"
Requires-Dist: werkzeug (>=2.2.1)
Project-URL: Repository, https://github.com/spec-first/connexion
